libprimo/__init__.py
libprimo-1.0.dist-info/LICENSE
libprimo-1.0.dist-info/METADATA
libprimo-1.0.dist-info/WHEEL
libprimo-1.0.dist-info/top_level.txt
libprimo-1.0.dist-info/RECORD
